hdbscan/__init__.py
hdbscan/_hdbscan_boruvka.cpython-310-darwin.so
hdbscan/_hdbscan_linkage.cpython-310-darwin.so
hdbscan/_hdbscan_reachability.cpython-310-darwin.so
hdbscan/_hdbscan_tree.cpython-310-darwin.so
hdbscan/_prediction_utils.cpython-310-darwin.so
hdbscan/branch_data.py
hdbscan/branches.py
hdbscan/dist_metrics.cpython-310-darwin.so
hdbscan/flat.py
hdbscan/hdbscan_.py
hdbscan/plots.py
hdbscan/prediction.py
hdbscan/robust_single_linkage_.py
hdbscan/validity.py
hdbscan/tests/__init__.py
hdbscan/tests/test_branches.py
hdbscan/tests/test_flat.py
hdbscan/tests/test_hdbscan.py
hdbscan/tests/test_prediction_utils.py
hdbscan/tests/test_rsl.py
hdbscan-0.8.41.data/data/dist_metrics.pxd
hdbscan-0.8.41.dist-info/licenses/LICENSE
hdbscan-0.8.41.dist-info/METADATA
hdbscan-0.8.41.dist-info/WHEEL
hdbscan-0.8.41.dist-info/top_level.txt
hdbscan-0.8.41.dist-info/RECORD
