Metadata-Version: 2.1
Name: hdbscan
Version: 0.8.41
Summary: Clustering based on density with variable density clusters
Home-page: http://github.com/scikit-learn-contrib/hdbscan
Maintainer: Leland McInnes
Maintainer-email: leland.mcinnes@gmail.com
License: BSD
Keywords: cluster clustering density hierarchical
Classifier: Development Status :: 4 - Beta
Classifier: Intended Audience :: Science/Research
Classifier: Intended Audience :: Developers
Classifier: License :: OSI Approved
Classifier: Programming Language :: C
Classifier: Programming Language :: Python
Classifier: Topic :: Software Development
Classifier: Topic :: Scientific/Engineering
Classifier: Operating System :: Microsoft :: Windows
Classifier: Operating System :: POSIX
Classifier: Operating System :: Unix
Classifier: Operating System :: MacOS
Classifier: Programming Language :: Python :: 3.10
Classifier: Programming Language :: Python :: 3.11
Classifier: Programming Language :: Python :: 3.12
Classifier: Programming Language :: Python :: 3.13
License-File: LICENSE
Requires-Dist: numpy<3,>=1.20
Requires-Dist: scipy>=1.0
Requires-Dist: scikit-learn>=1.6
Requires-Dist: joblib>=1.0
